jambazid/demo/__init__.py
jambazid/demo/cli.py
jambazid/demo/data/schema.json
jambazid/demo/module.py
jambazid/demo/py.typed
jambazid/demo/subpackage/__init__.py
jambazid/demo/subpackage/submodule.py
jambazid_uv_demo-0.0.16.dist-info/WHEEL
jambazid_uv_demo-0.0.16.dist-info/entry_points.txt
jambazid_uv_demo-0.0.16.dist-info/METADATA
jambazid_uv_demo-0.0.16.dist-info/RECORD
