Metadata-Version: 2.4
Name: jambazid-uv-demo
Version: 0.0.16
Summary: A minimal Python project template built with `uv`.
Author: Jambazid
Author-email: Jambazid <pypi@jambazid.dev>
License-Expression: MIT
Classifier: Development Status :: 2 - Pre-Alpha
Classifier: Topic :: Software Development :: Build Tools
Classifier: Topic :: Software Development :: Libraries :: Python Modules
Classifier: Topic :: Software Development :: Testing
Classifier: Topic :: Documentation
Classifier: Programming Language :: Python :: 3.11
Classifier: Programming Language :: Python :: 3.12
Classifier: Programming Language :: Python :: 3.13
Requires-Dist: typer>=0.20.0,<2
Requires-Dist: httpx>=0.28.1,<2
Requires-Dist: pydantic>=2.12,<3
Maintainer: Jambazid
Maintainer-email: Jambazid <pypi@jambazid.dev>
Requires-Python: >=3.11
Project-URL: Bug Tracker, https://github.com/jambazid/python-uv-template/issues
Project-URL: Homepage, https://poetry-demo.python.jambazid.dev
Project-URL: Repository, https://github.com/jambazid/python-uv-template
